README.md
setup.py
selectionfunctiontoolbox/__init__.py
selectionfunctiontoolbox/base.py
selectionfunctiontoolbox/chisel.py
selectionfunctiontoolbox/hammer.py
selectionfunctiontoolbox/kernel.py
selectionfunctiontoolbox/utils.py
selectionfunctiontoolbox/wrench.py
selectionfunctiontoolbox.egg-info/PKG-INFO
selectionfunctiontoolbox.egg-info/SOURCES.txt
selectionfunctiontoolbox.egg-info/dependency_links.txt
selectionfunctiontoolbox.egg-info/requires.txt
selectionfunctiontoolbox.egg-info/top_level.txt