Metadata-Version: 2.1
Name: selectionfunctiontoolbox
Version: 1.0.0
Summary: A set of tools for estimating the selection function of a scientific sample drawn from an astronomical catalogue.
Home-page: https://github.com/gaiaverse/selectionfunctiontoolbox
Author: Douglas Boubert & Andrew Everall
Author-email: ask@gaiaverse.space
License: GPLv2
Download-URL: https://github.com/gaiaverse/selectionfunctiontoolbox/archive/v1.0.0.tar.gz
Platform: UNKNOWN
